monitorat/__init__.py
monitorat/alerts.py
monitorat/auth.py
monitorat/cli.py
monitorat/config.py
monitorat/config_default.yaml
monitorat/federation.py
monitorat/monitor.py
monitorat/static/app.js
monitorat/static/favicon.ico
monitorat/static/index.html
monitorat/static/alerts/alerts.css
monitorat/static/alerts/alerts.js
monitorat/static/controls/controls.css
monitorat/static/controls/expansion.js
monitorat/static/controls/listing.js
monitorat/static/controls/notifications.js
monitorat/static/controls/reload.js
monitorat/static/controls/sorting.js
monitorat/static/editor/editor.css
monitorat/static/editor/editor.js
monitorat/static/editor/fields.css
monitorat/static/editor/fields.js
monitorat/static/editor/item.js
monitorat/static/header/header.css
monitorat/static/header/header.js
monitorat/static/history/charts.js
monitorat/static/history/corners.js
monitorat/static/history/history.css
monitorat/static/history/legends.js
monitorat/static/history/tables.js
monitorat/static/history/timeseries.js
monitorat/static/page/layout.js
monitorat/static/page/sections.js
monitorat/static/themes/default.css
monitorat/static/themes/formal.css
monitorat/static/tiles/tiles.css
monitorat/static/tiles/tiles.js
monitorat/static/tiles/tyler.tex
monitorat/static/ui/features.js
monitorat/static/ui/icons.js
monitorat/static/ui/indicators.js
monitorat/static/ui/modals.js
monitorat/widgets/__init__.py
monitorat/widgets/metrics/api.py
monitorat/widgets/metrics/app.js
monitorat/widgets/metrics/default.yaml
monitorat/widgets/metrics/index.html
monitorat/widgets/metrics/schema.json
monitorat/widgets/metrics/style.css
monitorat/widgets/metrics/features/snapshot.js
monitorat/widgets/metrics/features/history/chart.js
monitorat/widgets/metrics/features/history/table.js
monitorat/widgets/network/api.py
monitorat/widgets/network/app.js
monitorat/widgets/network/default.yaml
monitorat/widgets/network/index.html
monitorat/widgets/network/schema.json
monitorat/widgets/network/style.css
monitorat-0.11.1.dist-info/METADATA
monitorat-0.11.1.dist-info/WHEEL
monitorat-0.11.1.dist-info/entry_points.txt
monitorat-0.11.1.dist-info/licenses/LICENSE
monitorat-0.11.1.dist-info/RECORD
