Metadata-Version: 2.4
Name: monitorat
Version: 0.11.1
Summary: A federate, offline-friendly modular dashboard and documentation system for homelabs and Linux computers
Project-URL: Repository, https://github.com/brege/monitorat
Author-email: Wyatt Brege <wyatt@brege.org>
License:                     GNU GENERAL PUBLIC LICENSE
License-File: LICENSE
Classifier: Development Status :: 4 - Beta
Classifier: Framework :: Flask
Classifier: Intended Audience :: System Administrators
Classifier: License :: OSI Approved :: GNU General Public License v3 (GPLv3)
Classifier: Operating System :: POSIX :: Linux
Classifier: Programming Language :: Python :: 3
Classifier: Topic :: System :: Monitoring
Requires-Python: >=3.9
Requires-Dist: apprise>=1.4.0
Requires-Dist: confuse>=2.0.0
Requires-Dist: flask-httpauth>=4.8.0
Requires-Dist: flask>=3.0.0
Requires-Dist: gunicorn>=21.2.0
Requires-Dist: httpx>=0.27.0
Requires-Dist: psutil>=5.9.5
Requires-Dist: pytimeparse>=1.1.8
Requires-Dist: pyyaml>=6.0
Requires-Dist: schedule>=1.2.0
Requires-Dist: speedtest-cli>=2.1.3
